pyxcoder/__init__.py
pyxcoder/xfile/__init__.py
pyxcoder/xfile/xconvert.py
pyxcoder/xfile/xmain.py
pyxcoder/xfile/xmerged.py
pyxcoder/xfile/xreader.py
pyxcoder/xfile/xwriter.py
pyxcoder/xscript/__init__.py
pyxcoder-0.3.0.dist-info/METADATA
pyxcoder-0.3.0.dist-info/WHEEL
pyxcoder-0.3.0.dist-info/top_level.txt
pyxcoder-0.3.0.dist-info/RECORD
